pyxmp/__init__.py
pyxmp/pyxmp.py
tests/__init__.py
tests/test_pyxmp.py
pyxmp-0.1.1.dist-info/LICENSE
pyxmp-0.1.1.dist-info/METADATA
pyxmp-0.1.1.dist-info/WHEEL
pyxmp-0.1.1.dist-info/top_level.txt
pyxmp-0.1.1.dist-info/RECORD
