Metadata-Version: 2.1
Name: pyxmp
Version: 0.1.1
Summary: A Python XMP metadata injection tool based on py3exiv2.
Home-page: https://github.com/numbersprotocol/pyxmp
Author: Numbersprotocol
Author-email: hi@numbersprotocol.io
License: UNKNOWN
Platform: UNKNOWN
Requires-Python: >=3.6
Requires-Dist: py3exiv2
